MANIFEST.in
README.rst
setup.py
c2dx/__init__.py
c2dx/main.py
c2dx.egg-info/PKG-INFO
c2dx.egg-info/SOURCES.txt
c2dx.egg-info/dependency_links.txt
c2dx.egg-info/entry_points.txt
c2dx.egg-info/not-zip-safe
c2dx.egg-info/requires.txt
c2dx.egg-info/top_level.txt
c2dx/templates/.DS_Store
c2dx/templates/layer.cpp
c2dx/templates/layer.h