Metadata-Version: 1.0
Name: c2dx
Version: 1.0.1
Summary: Cocos2d-x Class Generator for C++
Home-page: https://bitbucket.org/cajun_code/c2dx.py
Author: Allan Davis
Author-email: cajun.code@gmail.com
License: MIT
Platform: UNKNOWN
